kflash.py
kflash-1.1.6.dist-info/LICENSE
kflash-1.1.6.dist-info/METADATA
kflash-1.1.6.dist-info/WHEEL
kflash-1.1.6.dist-info/entry_points.txt
kflash-1.1.6.dist-info/top_level.txt
kflash-1.1.6.dist-info/RECORD
