Metadata-Version: 2.1
Name: kflash
Version: 1.1.6
Summary: Kendryte UART ISP Utility - programming code to k210
Home-page: https://github.com/vowstar/kflash.py
Author: https://github.com/vowstar/kflash.py/graphs/contributors
Author-email: vowstar@gmail.com
Maintainer: Huang Rui
Maintainer-email: vowstar@gmail.com
License: MIT License
Platform: all
Classifier: Development Status :: 4 - Beta
Classifier: Operating System :: OS Independent
Classifier: Intended Audience :: Developers
Classifier: License :: OSI Approved :: MIT License
Classifier: Environment :: Console
Classifier: Natural Language :: English
Classifier: Programming Language :: Python
Classifier: Programming Language :: Python :: Implementation
Classifier: Programming Language :: Python :: 2.7
Classifier: Programming Language :: Python :: 3
Classifier: Programming Language :: Python :: 3.6
Classifier: Programming Language :: Python :: 3.7
Classifier: Programming Language :: Python :: 3.8
Classifier: Programming Language :: Python :: 3.9
Classifier: Programming Language :: Python :: 3.10
Classifier: Programming Language :: Python :: 3.11
Classifier: Topic :: Software Development :: Embedded Systems
License-File: LICENSE
Requires-Dist: pyserial (>=3.4)
Requires-Dist: pyelftools (>=0.25)
Requires-Dist: enum34 (>=1.1.10) ; python_version < "3.4.0"
